wsiserver/__init__.py
wsiserver/app.py
wsiserver-1.0.4.dist-info/LICENSE
wsiserver-1.0.4.dist-info/METADATA
wsiserver-1.0.4.dist-info/WHEEL
wsiserver-1.0.4.dist-info/entry_points.txt
wsiserver-1.0.4.dist-info/top_level.txt
wsiserver-1.0.4.dist-info/RECORD
