Metadata-Version: 2.1
Name: wsiserver
Version: 1.0.4
Summary: Very simple wsi server
Author-email: Takumi Ando <takumi.ando826@gmail.com>
License: Apache License
Classifier: Programming Language :: Python :: 3.6
Requires-Python: >=3.6
License-File: LICENSE
Requires-Dist: fastapi
Requires-Dist: openslide-python
Requires-Dist: pillow
Requires-Dist: uvicorn
